cho_check_os_ver-0.4.8.dist-info/METADATA
cho_check_os_ver-0.4.8.dist-info/WHEEL
cho_check_os_ver-0.4.8.dist-info/entry_points.txt
cho_check_os_ver/.osver.py.swp
cho_check_os_ver/__init__.py
cho_check_os_ver/hi.py
cho_check_os_ver/osver.py
cho_check_os_ver/randomimport.py
cho_check_os_ver/test_first.py
cho_check_os_ver-0.4.8.dist-info/RECORD
