Metadata-Version: 2.1
Name: cho-check-os-ver
Version: 0.4.8
Summary: Default template for PDM package
Author-Email: cho6019 <j01040864205@gmail.com>
License: MIT
Project-URL: Homepage, https://github.com/cho6019/cho-check-os-ver
Project-URL: Issues, https://github.com/cho6019/cho-check-os-ver/issues
Requires-Python: >=3.10
Requires-Dist: check_os_ver>=0.2.1
Requires-Dist: hj-check-os-version>=0.2.0
Requires-Dist: jacob-os-version-check>=0.2.4
Requires-Dist: lucas-check-os-ver>=0.2.0
Requires-Dist: stundrg-check-os-ver>=0.2.3
Requires-Dist: nunininu-check-os-ver>=0.2.0
Requires-Dist: seo-check-os-version>=0.2.0
